dll/libusb-1.0.dll
dll/lpamsdk.dll
dll/lpamsdk_d.dll
dll/pthreadVC2.dll
libs/libusb-1.0.lib
libs/libusb-1.0_d.lib
libs/lpamsdk.lib
libs/lpamsdk_d.lib
libs/pthreadVC2.lib
lpamsdk/__init__.py
lpamsdk-1.0.0.dist-info/licenses/LICENSE
lpamsdk-1.0.0.dist-info/METADATA
lpamsdk-1.0.0.dist-info/WHEEL
lpamsdk-1.0.0.dist-info/top_level.txt
lpamsdk-1.0.0.dist-info/RECORD
