Metadata-Version: 2.4
Name: lpamsdk
Version: 1.0.0
Summary: Python wrapper for LPAMSDK
Home-page: 
Author: Guannan Guo
Author-email: Guannan Guo <ggntju@outlook.com>
License-Expression: MIT
Project-URL: Homepage, https://github.com/ggntju/pyLPAMSDK
Project-URL: Issues, https://github.com/ggntju/pyLPAMSDK/issues
Classifier: Programming Language :: Python :: 3
Classifier: Operating System :: Microsoft :: Windows
Requires-Python: >=3.9
License-File: LICENSE
Dynamic: author
Dynamic: license-file
Dynamic: requires-python
